ubiops_file_sync/__init__.py
ubiops_file_sync/config.py
ubiops_file_sync/downloader.py
ubiops_file_sync/info.py
ubiops_file_sync/sync.py
ubiops_file_sync/uploader.py
ubiops_file_sync/watcher.py
ubiops_file_sync-0.1.8.dist-info/METADATA
ubiops_file_sync-0.1.8.dist-info/WHEEL
ubiops_file_sync-0.1.8.dist-info/licenses/LICENSE
ubiops_file_sync-0.1.8.dist-info/RECORD
