Metadata-Version: 2.4
Name: ubiops-file-sync
Version: 0.1.8
Summary: A Python library for synchronizing files between a local directory and a UbiOps bucket. This library provides utilities for downloading files from UbiOps buckets, uploading files to buckets, and automatically watching local directories for changes to keep them in sync with remote storage.
License-Expression: GPL-3.0-only
License-File: LICENSE
Requires-Python: >=3.12
Requires-Dist: backoff>=2.2.1
Requires-Dist: httpx>=0.28.1
Requires-Dist: pydantic>=2.11.7
Requires-Dist: ubiops==4.11.0
Requires-Dist: watchdog>=6.0.0
Provides-Extra: dev
Requires-Dist: detect-secrets>=1.5.0; extra == 'dev'
Requires-Dist: ipykernel>=7.1.0; extra == 'dev'
Requires-Dist: pre-commit>=4.3.0; extra == 'dev'
Requires-Dist: pydantic>=2.11.7; extra == 'dev'
Requires-Dist: pytest>=8.4.2; extra == 'dev'
Requires-Dist: ruff>=0.14.1; extra == 'dev'
Requires-Dist: ubiops-cli==2.28.0; extra == 'dev'
